au/__init__.py
au/base.py
au/backends/__init__.py
au/backends/rq_backend.py
au/backends/supabase_backend.py
au-0.0.16.dist-info/licenses/LICENSE
au-0.0.16.dist-info/METADATA
au-0.0.16.dist-info/WHEEL
au-0.0.16.dist-info/top_level.txt
au-0.0.16.dist-info/RECORD
