Metadata-Version: 2.4
Name: au
Version: 0.0.16
Summary: Async Utils
Home-page: https://github.com/i2mint/au
License: mit
Platform: any
License-File: LICENSE
Dynamic: license-file
